ftuple/.__init__.py.swp
ftuple/.__init__.py.un~
ftuple/__init__.py
ftuple-1.0.0.dist-info/LICENSE
ftuple-1.0.0.dist-info/WHEEL
ftuple-1.0.0.dist-info/METADATA
ftuple-1.0.0.dist-info/RECORD
