Metadata-Version: 1.2
Name: ftuple
Version: 1.0.0
Summary: F-strings are fabulous, why can't we make the same with Tuple and lists ?
Home-page: https://github.com/Carreau/ftuple
License: UNKNOWN
Author: Matthias Bussonnier
Author-email: bussonniermatthias@gmail.com
Classifier: License :: OSI Approved :: MIT License
